__test__.py
tggrok/__init__.py
tggrok/grok.py
tggrok-0.1.3.dist-info/licenses/LICENSE.txt
tggrok-0.1.3.dist-info/METADATA
tggrok-0.1.3.dist-info/WHEEL
tggrok-0.1.3.dist-info/top_level.txt
tggrok-0.1.3.dist-info/RECORD
