Metadata-Version: 2.4
Name: tggrok
Version: 0.1.3
Summary: Access GrokAI through Telegram
Author-email: Emelianov Artem <polyfoam3758@proton.me>
License: MIT License
Project-URL: Homepage, https://github.com/yaz008/tggrok
Keywords: telegram,pyrogram,api,llm,grok
Classifier: Programming Language :: Python :: 3
Classifier: License :: OSI Approved :: MIT License
Classifier: Operating System :: OS Independent
Requires-Python: >=3.13
License-File: LICENSE.txt
Requires-Dist: Pyrogram
Requires-Dist: TgCrypto
Requires-Dist: python-dotenv
Requires-Dist: jsonschema
Requires-Dist: cattrs
Provides-Extra: dev
Requires-Dist: isort; extra == "dev"
Requires-Dist: black; extra == "dev"
Requires-Dist: flake8-pyproject; extra == "dev"
Requires-Dist: mypy; extra == "dev"
Requires-Dist: pre-commit; extra == "dev"
Provides-Extra: pypi
Requires-Dist: build; extra == "pypi"
Requires-Dist: twine; extra == "pypi"
Dynamic: license-file
